bofa_scraper/__init__.py
bofa_scraper/account.py
bofa_scraper/scrape_session.py
bofa_scraper/util.py
bofa_scraper-1.0.2.dist-info/LICENSE
bofa_scraper-1.0.2.dist-info/METADATA
bofa_scraper-1.0.2.dist-info/WHEEL
bofa_scraper-1.0.2.dist-info/top_level.txt
bofa_scraper-1.0.2.dist-info/RECORD
