Metadata-Version: 2.1
Name: bofa-scraper
Version: 1.0.2
Summary: Simple Python web-scraper to get personal transaction data from BofA account.
Author-email: Wllew4 <willjanelle2@gmail.com>
License: GNU General Public License v3 (GPLv3) (GPL3)
Project-URL: Homepage, https://github.com/Wllew4/bofa_scraper
License-File: LICENSE
Requires-Dist: selenium
